provider_switch/__init__.py
provider_switch/exceptions.py
provider_switch/provider_collection.py
provider_switch/provider_switch_handler.py
provider_switch/constants/__init__.py
provider_switch/constants/core_constants.py
provider_switch/helpers/__init__.py
provider_switch/helpers/common_helper.py
provider_switch/helpers/dotdictify.py
provider_switch/helpers/mapping_data.py
provider_switch/helpers/response_helper.py
provider_switch/models/__init__.py
provider_switch/models/provider_model.py
provider_switch/ssm/__init__.py
provider_switch/ssm/ssm_client.py
provider_switch/utils/__init__.py
provider_switch/utils/common.py
provider_switch/utils/notify_service.py
provider_switch-0.0.34.dist-info/LICENSE.txt
provider_switch-0.0.34.dist-info/METADATA
provider_switch-0.0.34.dist-info/WHEEL
provider_switch-0.0.34.dist-info/top_level.txt
provider_switch-0.0.34.dist-info/RECORD
