Metadata-Version: 2.1
Name: provider-switch
Version: 0.0.34
Summary: provider-switch
Download-URL: https://pypi.org/project/provider-switch/
Author: Tai Nguyen
Author-email: tai.nguyen@hiip.asia
License: MIT
Keywords: Python 3
License-File: LICENSE.txt
Requires-Dist: boto3
